{
  "imported_at": "2026-03-30T10:54:31",
  "identity": {
    "title": "ストラテジーテスターレポート",
    "ea_name": "btcusd_20260124",
    "symbol": "BTCUSD",
    "timeframe": "M1",
    "tested_range": "2026.02.12 - 2026.02.19",
    "report_kind": "single_test_report"
  },
  "storage": {
    "ea_key": "btcusd-20260124",
    "symbol_key": "btcusd",
    "timeframe_key": "m1",
    "run_path": "reports/backtest/runs/btcusd-20260124/btcusd/m1/2026-03-30-105431-754831-btcusd-20260124-week1.json",
    "knowledge_path": "knowledge/backtests/btcusd-20260124/btcusd/m1/2026-03-30-105431-754831-btcusd-20260124-week1.md",
    "imported_dir": "reports/backtest/imported/btcusd-20260124/btcusd/m1/2026-03-30-105431-754831-btcusd-20260124-week1",
    "imported_report": "reports/backtest/imported/btcusd-20260124/btcusd/m1/2026-03-30-105431-754831-btcusd-20260124-week1/report.htm"
  },
  "source": {
    "original_path": "C:\\Users\\windows\\AppData\\Roaming\\MetaQuotes\\Terminal\\2FA8A7E69CED7DC259B1AD86A247F675\\MQL5\\Experts\\dev\\reports\\backtest\\imported\\btcusd_20260124-week1.htm",
    "type": "htm"
  },
  "metrics": {
    "ea_name": "btcusd_20260124",
    "symbol": "BTCUSD",
    "period": "M1 (2026.02.12 - 2026.02.19)",
    "history_quality_percent": 100.0,
    "bars": 10080,
    "ticks": 1546119,
    "initial_deposit": 10000.0,
    "total_net_profit": -666.71,
    "gross_profit": 1031.42,
    "gross_loss": -1698.13,
    "profit_factor": 0.61,
    "expected_payoff": -27.78,
    "recovery_factor": -0.78,
    "sharpe_ratio": -5.0,
    "absolute_drawdown": 666.71,
    "maximal_drawdown_amount": 817.71,
    "maximal_drawdown_percent": 8.06,
    "relative_drawdown_amount": 817.71,
    "relative_drawdown_percent": 8.06,
    "total_trades": 24,
    "short_positions_count": 12,
    "short_positions_percent": 33.33,
    "long_positions_count": 12,
    "long_positions_percent": 25.0,
    "profit_trades_count": 7,
    "profit_trades_percent": 29.17,
    "loss_trades_count": 17,
    "loss_trades_percent": 70.83,
    "largest_profit_trade": 156.75,
    "largest_loss_trade": -108.6,
    "average_profit_trade": 147.35,
    "average_loss_trade": -99.89,
    "timeframe": "M1",
    "tested_range": "2026.02.12 - 2026.02.19",
    "win_rate_percent": 29.17
  },
  "summary": {
    "headline": "取引回数が少なすぎて判断が不安定です。 / Profit Factor が 1.0 未満で、収益性はまだ不足しています。",
    "strengths": [
      "ドローダウンは比較的抑えられています。"
    ],
    "weak_points": [
      "取引回数が少なすぎて判断が不安定です。",
      "Profit Factor が 1.0 未満で、収益性はまだ不足しています。",
      "総損益がプラスではありません。"
    ],
    "notes": []
  },
  "tags": [
    "tuned-pass-6",
    "week1"
  ],
  "raw_fields": {
    "expert": "btcusd_20260124",
    "symbol": [
      "BTCUSD",
      "1"
    ],
    "period": "M1 (2026.02.12 - 2026.02.19)",
    "initial deposit": "10 000.00",
    "history quality": "100% リアルティック",
    "bars": "10080",
    "ticks": "1546119",
    "total net profit": "-666.71",
    "absolute drawdown": "666.71",
    "gross profit": "1 031.42",
    "maximal drawdown": "817.71 (8.06%)",
    "gross loss": "-1 698.13",
    "relative drawdown": "8.06% (817.71)",
    "profit factor": "0.61",
    "expected payoff": "-27.78",
    "recovery factor": "-0.78",
    "sharpe ratio": "-5.00",
    "z score": "1.83 (93.28%)",
    "ahpr": "0.9972 (-0.28%)",
    "lr correlation": "-0.93",
    "ontester": "0",
    "ghpr": "0.9971 (-0.29%)",
    "lr standard error": "90.09",
    "total trades": "24",
    "short trades won percent": "12 (33.33%)",
    "long positions won percent": "12 (25.00%)",
    "profit trades percent of total": "7 (29.17%)",
    "loss trades percent of total": "17 (70.83%)",
    "largest profit trade": "156.75",
    "largest loss trade": "-108.60",
    "average profit trade": "147.35",
    "average loss trade": "-99.89",
    "correlation profits mfe": "0.89",
    "correlation profits mae": "0.70",
    "correlation mfe mae": "0.6142",
    "t p": "時間",
    "2": [
      "BTCUSD",
      "BTCUSD",
      "0.00"
    ],
    "sell": [
      "1.66 / 1.66",
      "1.69 / 1.69",
      "1.67 / 1.67",
      "1.65 / 1.65",
      "1.64 / 1.64",
      "1.62 / 1.62",
      "1.64 / 1.64",
      "1.63 / 1.63",
      "1.65 / 1.65",
      "1.63 / 1.63",
      "1.62 / 1.62",
      "1.64 / 1.64",
      "1.63 / 1.63",
      "1.61 / 1.61",
      "1.59 / 1.59",
      "1.58 / 1.58",
      "1.6 / 1.6",
      "1.59 / 1.59",
      "1.57 / 1.57",
      "1.55 / 1.55",
      "1.58 / 1.58",
      "1.56 / 1.56",
      "1.58 / 1.58",
      "1.57 / 1.57",
      "in",
      "in",
      "in",
      "out",
      "out",
      "out",
      "out",
      "out",
      "out",
      "out",
      "in",
      "in",
      "in",
      "out",
      "out",
      "out",
      "out",
      "out",
      "in",
      "in",
      "in",
      "in",
      "in",
      "in"
    ],
    "0 00": [
      "67616.51",
      "2026.02.12 00:36:27",
      "67543.30",
      "2026.02.12 00:39:43",
      "67402.69",
      "2026.02.12 01:17:10",
      "65796.68",
      "2026.02.13 00:00:33",
      "65900.97",
      "2026.02.13 00:41:17",
      "68930.24",
      "2026.02.14 02:53:25",
      "68991.86",
      "2026.02.14 03:03:35",
      "69181.15",
      "2026.02.14 10:01:38",
      "69544.99",
      "2026.02.14 10:13:17",
      "69715.53",
      "2026.02.14 10:51:03",
      "69883.06",
      "2026.02.15 02:12:41",
      "69753.57",
      "2026.02.15 02:19:42",
      "69681.34",
      "2026.02.15 02:49:53",
      "68804.58",
      "2026.02.16 00:13:44",
      "68993.58",
      "2026.02.16 00:45:00",
      "68694.40",
      "2026.02.17 00:12:00",
      "68744.54",
      "2026.02.17 00:17:09",
      "68664.75",
      "2026.02.17 01:27:33",
      "67629.80",
      "2026.02.18 00:18:47",
      "67576.85",
      "2026.02.18 01:08:42",
      "67513.84",
      "2026.02.18 01:16:49",
      "67340.68",
      "2026.02.18 03:04:44",
      "67195.35",
      "2026.02.18 03:20:51",
      "67132.93",
      "2026.02.18 03:56:44",
      "0.00",
      "0.00",
      "151.00",
      "0.00",
      "-101.60",
      "0.00",
      "-106.03",
      "0.00",
      "-99.38",
      "0.00",
      "-108.60",
      "0.00",
      "146.22",
      "0.00",
      "-99.40",
      "0.00",
      "156.75",
      "0.00",
      "-99.51",
      "0.00",
      "-98.01",
      "0.00",
      "152.36",
      "0.00",
      "-101.18",
      "0.00",
      "-98.62",
      "0.00",
      "-97.37",
      "0.00",
      "-100.68",
      "0.00",
      "142.25",
      "0.00",
      "-97.44",
      "0.00",
      "-97.94",
      "0.00",
      "-94.64",
      "0.00",
      "141.86",
      "0.00",
      "-95.10",
      "0.00",
      "140.98",
      "0.00",
      "-105.78",
      "0.00",
      "-96.85",
      "0.00"
    ],
    "67466 51": "2026.02.12 00:30:00",
    "filled": [
      "EMA Scalper L1 SELL",
      "tp 67466.51",
      "EMA Scalper L1 SELL",
      "sl 67543.30",
      "EMA Scalper L1 SELL",
      "sl 67402.69",
      "EMA Scalper L3 BUY",
      "sl 65796.68",
      "EMA Scalper L1 BUY",
      "sl 65900.97",
      "EMA Scalper L1 BUY",
      "tp 69080.24",
      "EMA Scalper L1 BUY",
      "sl 68991.86",
      "EMA Scalper L1 BUY",
      "tp 69331.15",
      "EMA Scalper L4 BUY",
      "sl 69544.99",
      "EMA Scalper L1 BUY",
      "sl 69715.53",
      "EMA Scalper L1 SELL",
      "tp 69733.06",
      "EMA Scalper L1 SELL",
      "sl 69753.57",
      "EMA Scalper L3 SELL",
      "sl 69681.34",
      "EMA Scalper L3 BUY",
      "sl 68804.58",
      "EMA Scalper L3 BUY",
      "sl 68993.58",
      "EMA Scalper L3 BUY",
      "tp 68844.40",
      "EMA Scalper L3 BUY",
      "sl 68744.54",
      "EMA Scalper L1 BUY",
      "sl 68664.75",
      "EMA Scalper L1 SELL",
      "sl 67629.80",
      "EMA Scalper L1 SELL",
      "tp 67426.85",
      "EMA Scalper L1 SELL",
      "sl 67513.84",
      "EMA Scalper L3 SELL",
      "tp 67190.68",
      "EMA Scalper L1 SELL",
      "sl 67195.35",
      "EMA Scalper L3 SELL",
      "sl 67132.93"
    ],
    "3": [
      "BTCUSD",
      "BTCUSD",
      "0.00"
    ],
    "buy": [
      "1.66 / 1.66",
      "1.69 / 1.69",
      "1.67 / 1.67",
      "1.65 / 1.65",
      "1.64 / 1.64",
      "1.62 / 1.62",
      "1.64 / 1.64",
      "1.63 / 1.63",
      "1.65 / 1.65",
      "1.63 / 1.63",
      "1.62 / 1.62",
      "1.64 / 1.64",
      "1.63 / 1.63",
      "1.61 / 1.61",
      "1.59 / 1.59",
      "1.58 / 1.58",
      "1.6 / 1.6",
      "1.59 / 1.59",
      "1.57 / 1.57",
      "1.55 / 1.55",
      "1.58 / 1.58",
      "1.56 / 1.56",
      "1.58 / 1.58",
      "1.57 / 1.57",
      "out",
      "out",
      "out",
      "in",
      "in",
      "in",
      "in",
      "in",
      "in",
      "in",
      "out",
      "out",
      "out",
      "in",
      "in",
      "in",
      "in",
      "in",
      "out",
      "out",
      "out",
      "out",
      "out",
      "out"
    ],
    "4": [
      "BTCUSD",
      "BTCUSD",
      "0.00"
    ],
    "67393 30": "2026.02.12 00:39:00",
    "5": [
      "BTCUSD",
      "BTCUSD",
      "0.00"
    ],
    "6": [
      "BTCUSD",
      "BTCUSD",
      "0.00"
    ],
    "67252 69": "2026.02.12 01:17:00",
    "7": [
      "BTCUSD",
      "BTCUSD",
      "0.00"
    ],
    "8": [
      "BTCUSD",
      "BTCUSD",
      "0.00"
    ],
    "65946 68": "2026.02.13 00:00:00",
    "9": [
      "BTCUSD",
      "BTCUSD",
      "0.00"
    ],
    "10": [
      "BTCUSD",
      "BTCUSD",
      "0.00"
    ],
    "66050 97": "2026.02.13 00:40:00",
    "11": [
      "BTCUSD",
      "BTCUSD",
      "0.00"
    ],
    "12": [
      "BTCUSD",
      "BTCUSD",
      "0.00"
    ],
    "69080 24": "2026.02.14 02:48:00",
    "13": [
      "BTCUSD",
      "BTCUSD",
      "0.00"
    ],
    "14": [
      "BTCUSD",
      "BTCUSD",
      "0.00"
    ],
    "69141 86": "2026.02.14 02:56:03",
    "15": [
      "BTCUSD",
      "BTCUSD",
      "0.00"
    ],
    "16": [
      "BTCUSD",
      "BTCUSD",
      "0.00"
    ],
    "69331 15": "2026.02.14 09:57:00",
    "17": [
      "BTCUSD",
      "BTCUSD",
      "0.00"
    ],
    "18": [
      "BTCUSD",
      "BTCUSD",
      "0.00"
    ],
    "69694 99": "2026.02.14 10:13:00",
    "19": [
      "BTCUSD",
      "BTCUSD",
      "0.00"
    ],
    "20": [
      "BTCUSD",
      "BTCUSD",
      "0.00"
    ],
    "69865 53": "2026.02.14 10:51:00",
    "21": [
      "BTCUSD",
      "BTCUSD",
      "0.00"
    ],
    "22": [
      "BTCUSD",
      "BTCUSD",
      "0.00"
    ],
    "69733 06": "2026.02.15 01:31:00",
    "23": [
      "BTCUSD",
      "BTCUSD",
      "0.00"
    ],
    "24": [
      "BTCUSD",
      "BTCUSD",
      "0.00"
    ],
    "69603 57": "2026.02.15 02:19:00",
    "25": [
      "BTCUSD",
      "BTCUSD",
      "0.00"
    ],
    "26": [
      "BTCUSD",
      "BTCUSD",
      "0.00"
    ],
    "69531 34": "2026.02.15 02:49:00",
    "27": [
      "BTCUSD",
      "BTCUSD",
      "0.00"
    ],
    "28": [
      "BTCUSD",
      "BTCUSD",
      "0.00"
    ],
    "68954 58": "2026.02.16 00:04:00",
    "29": [
      "BTCUSD",
      "BTCUSD",
      "0.00"
    ],
    "30": [
      "BTCUSD",
      "BTCUSD",
      "0.00"
    ],
    "69143 58": "2026.02.16 00:45:00",
    "31": [
      "BTCUSD",
      "BTCUSD",
      "0.00"
    ],
    "32": [
      "BTCUSD",
      "BTCUSD",
      "0.00"
    ],
    "68844 40": "2026.02.17 00:10:00",
    "33": [
      "BTCUSD",
      "BTCUSD",
      "0.00"
    ],
    "34": [
      "BTCUSD",
      "BTCUSD",
      "0.00"
    ],
    "68894 54": "2026.02.17 00:16:00",
    "35": [
      "BTCUSD",
      "BTCUSD",
      "0.00"
    ],
    "36": [
      "BTCUSD",
      "BTCUSD",
      "0.00"
    ],
    "68814 75": "2026.02.17 01:18:02",
    "37": [
      "BTCUSD",
      "BTCUSD",
      "0.00"
    ],
    "38": [
      "BTCUSD",
      "BTCUSD",
      "0.00"
    ],
    "67479 80": "2026.02.18 00:18:00",
    "39": [
      "BTCUSD",
      "BTCUSD",
      "0.00"
    ],
    "40": [
      "BTCUSD",
      "BTCUSD",
      "0.00"
    ],
    "67426 85": "2026.02.18 01:06:00",
    "41": [
      "BTCUSD",
      "BTCUSD",
      "0.00"
    ],
    "42": [
      "BTCUSD",
      "BTCUSD",
      "0.00"
    ],
    "67363 84": "2026.02.18 01:15:00",
    "43": [
      "BTCUSD",
      "BTCUSD",
      "0.00"
    ],
    "44": [
      "BTCUSD",
      "BTCUSD",
      "0.00"
    ],
    "67190 68": "2026.02.18 03:03:00",
    "45": [
      "BTCUSD",
      "BTCUSD",
      "0.00"
    ],
    "46": [
      "BTCUSD",
      "BTCUSD",
      "0.00"
    ],
    "67045 35": "2026.02.18 03:14:00",
    "47": [
      "BTCUSD",
      "BTCUSD",
      "0.00"
    ],
    "48": [
      "BTCUSD",
      "BTCUSD",
      "0.00"
    ],
    "66982 93": "2026.02.18 03:54:00",
    "49": [
      "BTCUSD",
      "BTCUSD",
      "0.00"
    ],
    "1": "balance",
    "10 000 00": [
      "10 000.00",
      "EMA Scalper L1 SELL"
    ],
    "1 66": [
      "67556.51",
      "67465.55"
    ],
    "10 151 00": [
      "tp 67466.51",
      "EMA Scalper L1 SELL"
    ],
    "1 69": [
      "67483.30",
      "67543.42"
    ],
    "10 049 40": [
      "sl 67543.30",
      "EMA Scalper L1 SELL"
    ],
    "1 67": [
      "67342.69",
      "67406.18"
    ],
    "9 943 37": [
      "sl 67402.69",
      "EMA Scalper L3 BUY"
    ],
    "1 65": [
      "65856.68",
      "65796.45",
      "69604.99",
      "69544.68"
    ],
    "9 843 99": [
      "sl 65796.68",
      "EMA Scalper L1 BUY"
    ],
    "1 64": [
      "65960.97",
      "65894.75",
      "69051.86",
      "68991.25",
      "69693.57",
      "69755.26"
    ],
    "9 735 39": [
      "sl 65900.97",
      "EMA Scalper L1 BUY"
    ],
    "1 62": [
      "68990.24",
      "69080.50",
      "69823.06",
      "69729.01"
    ],
    "9 881 61": [
      "tp 69080.24",
      "EMA Scalper L1 BUY"
    ],
    "9 782 21": [
      "sl 68991.86",
      "EMA Scalper L1 BUY"
    ],
    "1 63": [
      "69241.15",
      "69337.31",
      "69775.53",
      "69715.40",
      "69621.34",
      "69681.84"
    ],
    "9 938 96": [
      "tp 69331.15",
      "EMA Scalper L4 BUY"
    ],
    "9 839 45": [
      "sl 69544.99",
      "EMA Scalper L1 BUY"
    ],
    "9 741 44": [
      "sl 69715.53",
      "EMA Scalper L1 SELL"
    ],
    "9 893 80": [
      "tp 69733.06",
      "EMA Scalper L1 SELL"
    ],
    "9 792 62": [
      "sl 69753.57",
      "EMA Scalper L3 SELL"
    ],
    "9 694 00": [
      "sl 69681.34",
      "EMA Scalper L3 BUY"
    ],
    "1 61": [
      "68864.58",
      "68804.10"
    ],
    "9 596 63": [
      "sl 68804.58",
      "EMA Scalper L3 BUY"
    ],
    "1 59": [
      "69053.58",
      "68990.26",
      "68724.75",
      "68663.15"
    ],
    "9 495 95": [
      "sl 68993.58",
      "EMA Scalper L3 BUY"
    ],
    "1 58": [
      "68754.40",
      "68844.43",
      "67453.84",
      "67514.03",
      "67135.35",
      "67202.30"
    ],
    "9 638 20": [
      "tp 68844.40",
      "EMA Scalper L3 BUY"
    ],
    "1 6": [
      "68804.54",
      "68743.64"
    ],
    "9 540 76": [
      "sl 68744.54",
      "EMA Scalper L1 BUY"
    ],
    "9 442 82": [
      "sl 68664.75",
      "EMA Scalper L1 SELL"
    ],
    "1 57": [
      "67569.80",
      "67630.08",
      "67072.93",
      "67134.62"
    ],
    "9 348 18": [
      "sl 67629.80",
      "EMA Scalper L1 SELL"
    ],
    "1 55": [
      "67516.85",
      "67425.33"
    ],
    "9 490 04": [
      "tp 67426.85",
      "EMA Scalper L1 SELL"
    ],
    "9 394 94": [
      "sl 67513.84",
      "EMA Scalper L3 SELL"
    ],
    "1 56": [
      "67280.68",
      "67190.31"
    ],
    "9 535 92": [
      "tp 67190.68",
      "EMA Scalper L1 SELL"
    ],
    "9 430 14": [
      "sl 67195.35",
      "EMA Scalper L3 SELL"
    ],
    "9 333 29": "sl 67132.93",
    "666 71": "9 333.29"
  },
  "records_preview": [],
  "run_id": "2026-03-30-105431-754831-btcusd-20260124-week1"
}
